dictdb/__init__.py
dictdb/exceptions.py
dictdb/py.typed
dictdb/core/__init__.py
dictdb/core/condition.py
dictdb/core/field.py
dictdb/core/rwlock.py
dictdb/core/table.py
dictdb/core/types.py
dictdb/index/__init__.py
dictdb/index/avl.py
dictdb/index/base.py
dictdb/index/hash.py
dictdb/index/registry.py
dictdb/index/sorted.py
dictdb/obs/__init__.py
dictdb/obs/logging.py
dictdb/query/__init__.py
dictdb/query/aggregate.py
dictdb/query/order.py
dictdb/query/pager.py
dictdb/query/projection.py
dictdb/storage/__init__.py
dictdb/storage/backup.py
dictdb/storage/csv_io.py
dictdb/storage/database.py
dictdb/storage/persist.py
dctdb-1.11.0.dist-info/METADATA
dctdb-1.11.0.dist-info/WHEEL
dctdb-1.11.0.dist-info/licenses/LICENSE
dctdb-1.11.0.dist-info/RECORD
