Metadata-Version: 2.4
Name: dctdb
Version: 1.11.0
Summary: Pure Python in-memory database with SQL-like queries
Project-URL: Homepage, https://github.com/mhbxyz/dictdb
Project-URL: Documentation, https://mhbxyz.github.io/dictdb
Project-URL: Repository, https://github.com/mhbxyz/dictdb
Project-URL: Issues, https://github.com/mhbxyz/dictdb/issues
Author-email: Manoah Bernier <manoah.bernier@gmail.com>
License-Expression: Apache-2.0
License-File: LICENSE
Keywords: database,dictionary,in-memory,index,orm,query,sql
Classifier: Development Status :: 5 - Production/Stable
Classifier: Intended Audience :: Developers
Classifier: License :: OSI Approved :: Apache Software License
Classifier: Operating System :: OS Independent
Classifier: Programming Language :: Python :: 3
Classifier: Programming Language :: Python :: 3.13
Classifier: Topic :: Database
Classifier: Topic :: Software Development :: Libraries :: Python Modules
Classifier: Typing :: Typed
Requires-Python: >=3.13
